s2a_sdk/__init__.py
s2a_sdk/client.py
s2a_sdk/enums.py
s2a_sdk/models.py
s2a_sdk/utils.py
s2a_sdk-1.0.4.dist-info/METADATA
s2a_sdk-1.0.4.dist-info/WHEEL
s2a_sdk-1.0.4.dist-info/top_level.txt
s2a_sdk-1.0.4.dist-info/RECORD
