Metadata-Version: 2.4
Name: s2a-sdk
Version: 1.0.4
Summary: Official Python SDK for S2A Speech-to-Actions Platform
Home-page: https://github.com/99technologies-ai/s2a-sdk-python
Author: 99Technologies AI
Author-email: support@99technologies.ai
Project-URL: Bug Reports, https://github.com/99technologies-ai/s2a/issues
Project-URL: Documentation, https://docs.bytepulseai.com/sdk/python
Project-URL: Source, https://github.com/99technologies-ai/s2a-sdk-python
Project-URL: API Reference, https://api.bytepulseai.com/docs
Keywords: speech-to-text transcription ai business-intelligence s2a audio nlp
Classifier: Development Status :: 4 - Beta
Classifier: Intended Audience :: Developers
Classifier: Topic :: Software Development :: Libraries :: Python Modules
Classifier: Topic :: Multimedia :: Sound/Audio :: Speech
Classifier: Topic :: Scientific/Engineering :: Artificial Intelligence
Classifier: License :: OSI Approved :: MIT License
Classifier: Programming Language :: Python :: 3
Classifier: Programming Language :: Python :: 3.8
Classifier: Programming Language :: Python :: 3.9
Classifier: Programming Language :: Python :: 3.10
Classifier: Programming Language :: Python :: 3.11
Classifier: Programming Language :: Python :: 3.12
Classifier: Operating System :: OS Independent
Requires-Python: >=3.8
Requires-Dist: httpx>=0.25.0
Requires-Dist: pydantic>=2.0.0
Requires-Dist: typing-extensions>=4.0.0
Requires-Dist: librosa>=0.10.0; extra == "audio"
Requires-Dist: soundfile>=0.12.0; extra == "audio"
Requires-Dist: pytest>=7.0.0; extra == "dev"
Requires-Dist: pytest-asyncio>=0.21.0; extra == "dev"
Requires-Dist: black>=23.0.0; extra == "dev"
Requires-Dist: flake8>=6.0.0; extra == "dev"
Provides-Extra: audio
Requires-Dist: librosa>=0.10.0; extra == "audio"
Requires-Dist: soundfile>=0.12.0; extra == "audio"
Provides-Extra: dev
Requires-Dist: pytest>=7.0.0; extra == "dev"
Requires-Dist: pytest-asyncio>=0.21.0; extra == "dev"
Requires-Dist: black; extra == "dev"
Requires-Dist: flake8; extra == "dev"
Provides-Extra: all
Requires-Dist: librosa>=0.10.0; extra == "all"
Requires-Dist: soundfile>=0.12.0; extra == "all"
Requires-Dist: pytest>=7.0.0; extra == "all"
Requires-Dist: pytest-asyncio>=0.21.0; extra == "all"
Requires-Dist: black; extra == "all"
Requires-Dist: flake8; extra == "all"
Dynamic: author
Dynamic: author-email
Dynamic: classifier
Dynamic: description
Dynamic: description-content-type
Dynamic: home-page
Dynamic: keywords
Dynamic: project-url
Dynamic: provides-extra
Dynamic: requires-dist
Dynamic: requires-python
Dynamic: summary
